LICENSE.txt
README.md
setup.py
taste/__init__.py
taste/plots.py
taste.egg-info/PKG-INFO
taste.egg-info/SOURCES.txt
taste.egg-info/dependency_links.txt
taste.egg-info/requires.txt
taste.egg-info/top_level.txt