Metadata-Version: 2.4
Name: taste
Version: 0.3.1
Author: Peter Badida
Author-email: keyweeusr@gmail.com
Classifier: Development Status :: 3 - Alpha
Classifier: License :: OSI Approved :: MIT License
Classifier: Operating System :: OS Independent
Classifier: Framework :: Jupyter
Classifier: Framework :: Matplotlib
Classifier: Topic :: Scientific/Engineering :: Visualization
Classifier: Intended Audience :: End Users/Desktop
Classifier: Intended Audience :: Science/Research
Classifier: Intended Audience :: Developers
Classifier: Natural Language :: English
Classifier: Programming Language :: Python
Classifier: Programming Language :: Python :: 3
Classifier: Programming Language :: Python :: 3.7
Classifier: Programming Language :: Python :: 3 :: Only
Classifier: Topic :: Utilities
Classifier: Typing :: Typed
Requires-Python: >=3.6
License-File: LICENSE.txt
Requires-Dist: ensure
Requires-Dist: matplotlib
Requires-Dist: pint
Provides-Extra: dev
Requires-Dist: pycodestyle; extra == "dev"
Requires-Dist: pylint; extra == "dev"
Provides-Extra: release
Requires-Dist: setuptools; extra == "release"
Requires-Dist: twine; extra == "release"
Provides-Extra: doc
Requires-Dist: sphinx>=3.0.4; extra == "doc"
Requires-Dist: nbsphinx; extra == "doc"
Requires-Dist: ipython; extra == "doc"
Dynamic: author
Dynamic: author-email
Dynamic: classifier
Dynamic: description
Dynamic: description-content-type
Dynamic: license-file
Dynamic: provides-extra
Dynamic: requires-dist
Dynamic: requires-python
